topsis_shantanu_102353013/__init__.py
topsis_shantanu_102353013/topsis.py
topsis_shantanu_102353013-1.0.0.dist-info/licenses/LICENSE
topsis_shantanu_102353013-1.0.0.dist-info/METADATA
topsis_shantanu_102353013-1.0.0.dist-info/WHEEL
topsis_shantanu_102353013-1.0.0.dist-info/entry_points.txt
topsis_shantanu_102353013-1.0.0.dist-info/top_level.txt
topsis_shantanu_102353013-1.0.0.dist-info/RECORD
