Metadata-Version: 2.4
Name: Topsis-Shantanu-102353013
Version: 1.0.0
Summary: A Python package for implementing TOPSIS (Technique for Order of Preference by Similarity to Ideal Solution)
Author: Shantanu Singhal
Author-email: example@email.com
Classifier: Programming Language :: Python :: 3
Classifier: License :: OSI Approved :: MIT License
Classifier: Operating System :: OS Independent
Requires-Python: >=3.6
License-File: LICENSE
Requires-Dist: pandas
Requires-Dist: numpy
Dynamic: author
Dynamic: author-email
Dynamic: classifier
Dynamic: description
Dynamic: description-content-type
Dynamic: license-file
Dynamic: requires-dist
Dynamic: requires-python
Dynamic: summary
